WICPy/README.md
WICPy/__init__.py
WICPy/comserver.c
WICPy/comserver.dll
WICPy/test.py
WICPy/wic.py
WICPy/test/sDCIP3.col
WICPy/test/test-p3.jpg
WICPy/test/test.jpg
WICPy/test/test.png
WICPy/test/test.tif
wicpy-1.3.0.dist-info/licenses/LICENSE
wicpy-1.3.0.dist-info/METADATA
wicpy-1.3.0.dist-info/WHEEL
wicpy-1.3.0.dist-info/top_level.txt
wicpy-1.3.0.dist-info/RECORD
