Metadata-Version: 2.4
Name: WICPy
Version: 1.3.0
Summary: A module in Python3 providing a bridge with the Windows Imaging Component (WIC) framework and helping the creation, marshaling and registration of custom COM interfaces
Home-page: https://github.com/PCigales/WICPy
Author: PCigales
License: GPL-3.0-or-later
Project-URL: Bug Tracker, https://github.com/PCigales/WICPy/issues
Keywords: wic,windows-imaging-component,image,metadata,direct2d,windows-shell,com
Platform: win64
Classifier: Programming Language :: Python :: 3
Classifier: Operating System :: Microsoft :: Windows
Classifier: Development Status :: 5 - Production/Stable
Classifier: Topic :: Software Development :: Libraries :: Python Modules
Classifier: Topic :: Multimedia :: Graphics
Classifier: Topic :: Multimedia :: Graphics :: Graphics Conversion
Requires-Python: >=3.8
License-File: LICENSE
Dynamic: license-file
